{
  "page_count": 1128,
  "errno": 0,
  "errmsg": "",
  "shop_data": [
    {
      "shop_id": "159157",
      "mer_type": "enterprise",
      "shop_name": "芯诚盛笔记本维修中心",
      "shop_ico": "http://p0.qhimg.com/t0104100555bb8b6c86.jpg",
      "mobile": "15926219968",
      "fixed_phone": "",
      "map_latitude": "30.58131781",
      "map_longitude": "114.28703249",
      "addr_city": "武汉",
      "addr_area": "江汉区",
      "addr_areaquan": "前进",
      "addr_detail": "武汉江汉区前进五路 前进电脑城 一楼 61室",
      "count": "230",
      "comments": "230",
      "addr_city_code": "wu_han",
      "main": "笔记本主板芯片级维修 笔记本配件批发 液晶显示器维修 清灰除尘 升级",
      "is_online": "off",
      "qid": "395895833",
      "shop_score": "5.0",
      "order_count": "230",
      "shop_visit": "12514",
      "is_liansuo": "0",
      "qita_renzheng": "",
      "is_cuxiao": "0",
      "is_bzj": "1",
      "last_ocount": "0",
      "jiameng_status": "40",
      "shop_addr": "http://1591575833.bang.360.cn/?from=index",
      "shop_desc": "笔记本主板芯片级维修 笔记本配件批发 液晶显示器维修 清灰除尘 升级",
      "cuxiao_tips": "",
      "addr": "武汉江汉区武汉江汉区前进五路 前进电脑城 一楼 61室",
      "s_shop_id": "1591575833",
      "infixed_phone": "",
      "score": "5.0",
      "sort_type": "",
      "bx30": 0,
      "grade": "6",
      "level": 7
    },
    {
      "shop_id": "161975",
      "mer_type": "enterprise",
      "shop_name": "可可电脑",
      "shop_ico": "http://p0.qhimg.com/t01ff88b7e9e90a52df.jpg",
      "mobile": "15387067960",
      "fixed_phone": "027-15387067-960",
      "map_latitude": "30.622864",
      "map_longitude": "114.391912",
      "addr_city": "武汉",
      "addr_area": "青山区",
      "addr_areaquan": "青山",
      "addr_detail": "武汉青山区友谊大道 和平大道 工业一路111西门（旁）可可电脑",
      "count": "34",
      "comments": "34",
      "addr_city_code": "wu_han",
      "main": "电脑维修，笔记本维修、网络工程、系统安装、显卡升级、上门服务",
      "is_online": "off",
      "qid": "17779109",
      "shop_score": "5.0",
      "order_count": "34",
      "shop_visit": "6110",
      "is_liansuo": "0",
      "qita_renzheng": "{\"renzheng_type\":\"\"}",
      "is_cuxiao": "0",
      "is_bzj": "1",
      "last_ocount": "0",
      "jiameng_status": "40",
      "shop_addr": "http://1619759109.bang.360.cn/?from=index",
      "shop_desc": "电脑维修，笔记本维修、网络工程、系统安装、显卡升级、上门服务",
      "cuxiao_tips": "",
      "addr": "武汉青山区武汉青山区友谊大道 和平大道 工业一路111西门（旁）可可电脑",
      "s_shop_id": "1619759109",
      "infixed_phone": "027****960",
      "score": "5.0",
      "sort_type": "",
      "bx30": 0,
      "grade": "6",
      "level": 6
    },
    {
      "shop_id": "171729",
      "mer_type": "enterprise",
      "shop_name": "天始实业计算机服务部",
      "shop_ico": "http://p0.qhimg.com/t01a5208702f421e528.jpg",
      "mobile": "13387570280",
      "fixed_phone": "027-87018220",
      "map_latitude": "30.34738",
      "map_longitude": "114.311369",
      "addr_city": "武汉",
      "addr_area": "江夏区",
      "addr_areaquan": "纸坊",
      "addr_detail": "武汉江夏区纸坊街军民巷",
      "count": "7",
      "comments": "7",
      "addr_city_code": "wu_han",
      "main": "计算机及办公通讯设备的批零、租赁、售后服务；软件和信息技术服务",
      "is_online": "off",
      "qid": "74229372",
      "shop_score": "5.0",
      "order_count": "7",
      "shop_visit": "800",
      "is_liansuo": "0",
      "qita_renzheng": "{\"closed_yingye\":{\"sdate\":\"2015-10-07\",\"edate\":\"2015-12-31\"}}",
      "is_cuxiao": "0",
      "is_bzj": "1",
      "last_ocount": "0",
      "jiameng_status": "40",
      "shop_addr": "http://1717299372.bang.360.cn/?from=index",
      "shop_desc": "计算机及办公通讯设备的批零、租赁、售后服务；软件和信息技术服务",
      "cuxiao_tips": "",
      "addr": "武汉江夏区武汉江夏区纸坊街军民巷",
      "s_shop_id": "1717299372",
      "infixed_phone": "027****220",
      "score": "5.0",
      "sort_type": "",
      "bx30": 0,
      "grade": "3",
      "level": 3
    },
    {
      "shop_id": "155609",
      "mer_type": "enterprise",
      "shop_name": "武汉阳逻影子电脑",
      "shop_ico": "http://p0.qhimg.com/t01fc193e9ba415b5f3.jpg",
      "mobile": "13437118001",
      "fixed_phone": "",
      "map_latitude": "30.65566189",
      "map_longitude": "114.5774889",
      "addr_city": "武汉",
      "addr_area": "新洲区",
      "addr_areaquan": "阳逻",
      "addr_detail": "武汉新洲区阳逻金融街延长线332号",
      "count": "30",
      "comments": "30",
      "addr_city_code": "wu_han",
      "main": "品牌电脑，笔记本电脑，组装电脑，安防监控等",
      "is_online": "on",
      "qid": "747432127",
      "shop_score": "5.0",
      "order_count": "30",
      "shop_visit": "7525",
      "is_liansuo": "0",
      "qita_renzheng": "{\"renzheng_type\":\"\"}",
      "is_cuxiao": "0",
      "is_bzj": "1",
      "last_ocount": "0",
      "jiameng_status": "40",
      "shop_addr": "http://1556092127.bang.360.cn/?from=index",
      "shop_desc": "品牌电脑，笔记本电脑，组装电脑，安防监控等",
      "cuxiao_tips": "",
      "addr": "武汉新洲区武汉新洲区阳逻金融街延长线332号",
      "s_shop_id": "1556092127",
      "infixed_phone": "",
      "score": "5.0",
      "sort_type": "",
      "bx30": 0,
      "grade": "3",
      "level": 3
    },
    {
      "shop_id": "172081",
      "mer_type": "person",
      "shop_name": "嘉诚电脑维修中心",
      "shop_ico": "http://p1.qhimg.com/t01eeec29774f9bbb3b.jpg",
      "mobile": "15377506507",
      "fixed_phone": "",
      "map_latitude": "30.627565",
      "map_longitude": "114.261139",
      "addr_city": "武汉",
      "addr_area": "江岸区",
      "addr_areaquan": "球场街",
      "addr_detail": "武汉江岸区球场路8号",
      "count": "17",
      "comments": "17",
      "addr_city_code": "wu_han",
      "main": "台式 笔记本 打印机维修 网络组建 维护",
      "is_online": "off",
      "qid": "404610689",
      "shop_score": "5.0",
      "order_count": "17",
      "shop_visit": "1048",
      "is_liansuo": "0",
      "qita_renzheng": "{\"renzheng_type\":\"\"}",
      "is_cuxiao": "0",
      "is_bzj": "1",
      "last_ocount": "0",
      "jiameng_status": "40",
      "shop_addr": "http://1720810689.bang.360.cn/?from=index",
      "shop_desc": "台式 笔记本 打印机维修 网络组建 维护",
      "cuxiao_tips": "",
      "addr": "武汉江岸区武汉江岸区球场路8号",
      "s_shop_id": "1720810689",
      "infixed_phone": "",
      "score": "5.0",
      "sort_type": "",
      "bx30": 0,
      "grade": "6",
      "level": 6
    }
  ]
}